crushon/__init__.py
crushon/client.py
crushon/lib/__init__.py
crushon/lib/characters.py
crushon-1.0.0.dist-info/METADATA
crushon-1.0.0.dist-info/WHEEL
crushon-1.0.0.dist-info/top_level.txt
crushon-1.0.0.dist-info/RECORD
