Metadata-Version: 2.1
Name: crushon
Version: 1.0.0
Summary: Crushon provides access to the Crushon.Ai API.
Home-page: https://github.com/RedPiarOfficial/Crushon-Ai
Author: RedPiar
Author-email: Redpiar.official@gmail.com
License: MIT
Project-URL: Source, https://github.com/RedPiarOfficial/Crushon-Ai
Keywords: artificial-intelligence,crushonAi,charactersAi,ai
Classifier: Programming Language :: Python :: 3
Classifier: License :: OSI Approved :: MIT License
Classifier: Operating System :: OS Independent
Requires-Python: >=3.8
Requires-Dist: cloudscraper
